bcirc/__init__.py
bcirc/circuits.py
bcirc-0.0.2.dist-info/LICENSE
bcirc-0.0.2.dist-info/METADATA
bcirc-0.0.2.dist-info/WHEEL
bcirc-0.0.2.dist-info/top_level.txt
bcirc-0.0.2.dist-info/RECORD
