Metadata-Version: 2.1
Name: bcirc
Version: 0.0.2
Summary: Boolean circuits package for my students
Home-page: https://github.com/pypigit/bcirc
Author: Tamas Hubai
Author-email: python@htamas.net
License: UNKNOWN
Platform: UNKNOWN
Classifier: Programming Language :: Python :: 3
Classifier: License :: OSI Approved :: MIT License
Classifier: Operating System :: OS Independent
